chem_wasserstein/ElM2D_.py
chem_wasserstein/ElM2D_0-4-0_ElMD_0-4-3.csv
chem_wasserstein/__init__.py
chem_wasserstein/meta.yaml
chem_wasserstein/stable-mp-500.csv
chem_wasserstein/test_ElM2D.py
chem_wasserstein/train-debug.csv
chem_wasserstein/utils/Timer.py
chem_wasserstein-1.0.12.dist-info/LICENSE
chem_wasserstein-1.0.12.dist-info/WHEEL
chem_wasserstein-1.0.12.dist-info/METADATA
chem_wasserstein-1.0.12.dist-info/RECORD
