Metadata-Version: 2.1
Name: chem_wasserstein
Version: 1.0.12
Summary: A high performance mapping class to construct ElM2D plots from large datasets of inorganic compositions.
Author-email: Cameron Hagreaves <cameron.h@rgreaves.me.uk>, "Sterling G. Baird" <sterling.baird@utah.edu>
Requires-Python: >=3.7
Classifier: License :: OSI Approved :: GNU General Public License v3 or later (GPLv3+)
Classifier: Development Status :: 5 - Production/Stable
Classifier: Intended Audience :: Developers
Classifier: Topic :: Software Development :: Build Tools
Classifier: Programming Language :: Python :: 3
Classifier: Programming Language :: Python :: 3.4
Classifier: Programming Language :: Python :: 3.5
Classifier: Programming Language :: Python :: 3.6
Classifier: Programming Language :: Python :: 3.7
Classifier: Programming Language :: Python :: 3.8
Classifier: Programming Language :: Python :: 3.9
Classifier: Programming Language :: Python :: 3.10
Requires-Dist: pqdm >=0.1.0
Requires-Dist: plotly
Requires-Dist: pandas
Requires-Dist: numba >=0.53.1
Requires-Dist: scipy
Requires-Dist: tqdm
Requires-Dist: colorama
Requires-Dist: umap-learn
Requires-Dist: dist_matrix >=1.0.2
Requires-Dist: ElMD ==0.4.8
Requires-Dist: scikit_learn
Project-URL: Home, https://github.com/sparks-baird/ElM2D
